[
  {
    "url": "/assets/images/gallery/1.jpg",
    "alt": "",
    "caption": ""
  },
  {
    "url": "/assets/images/gallery/2.jpg",
    "alt": "",
    "caption": ""
  },
  {
    "url": "/assets/images/gallery/3.jpg",
    "alt": "",
    "caption": ""
  },
  {
    "url": "/assets/images/gallery/4.jpg",
    "alt": "",
    "caption": ""
  },
  {
    "url": "/assets/images/gallery/5.jpg",
    "alt": "",
    "caption": ""
  },
  {
    "url": "/assets/images/gallery/6.jpg",
    "alt": "",
    "caption": ""
  },
  {
    "url": "/assets/images/gallery/7.jpg",
    "alt": "",
    "caption": ""
  },
  {
    "url": "/assets/images/gallery/8.jpg",
    "alt": "",
    "caption": ""
  },
  {
    "url": "/assets/images/gallery/9.jpg",
    "alt": "",
    "caption": ""
  },
  {
    "url": "/assets/images/gallery/10.jpg",
    "alt": "",
    "caption": ""
  },
  {
    "url": "/assets/images/gallery/11.jpg",
    "alt": "",
    "caption": ""
  },
  {
    "url": "/assets/images/gallery/12.jpg",
    "alt": "",
    "caption": ""
  },
  {
    "url": "/assets/images/gallery/13.jpg",
    "alt": "",
    "caption": ""
  },
  {
    "url": "/assets/images/gallery/14.jpg",
    "alt": "",
    "caption": ""
  },
  {
    "url": "/assets/images/gallery/15.jpg",
    "alt": "",
    "caption": ""
  },
  {
    "url": "/assets/images/gallery/16.jpg",
    "alt": "",
    "caption": ""
  },
  {
    "url": "/assets/images/gallery/17.jpg",
    "alt": "",
    "caption": ""
  },
  {
    "url": "/assets/images/gallery/18.jpg",
    "alt": "",
    "caption": ""
  },
  {
    "url": "/assets/images/gallery/19.jpg",
    "alt": "",
    "caption": ""
  },
  {
    "url": "/assets/images/gallery/20.jpg",
    "alt": "",
    "caption": ""
  },
]
